david_cointegration_package/Backtest.py
david_cointegration_package/Cointegration.py
david_cointegration_package/__init__.py
david_cointegration_package/python_class.py
david_cointegration_package-1.0.0.dist-info/LICENSE
david_cointegration_package-1.0.0.dist-info/METADATA
david_cointegration_package-1.0.0.dist-info/WHEEL
david_cointegration_package-1.0.0.dist-info/RECORD
